unitest/__init__.py
unitest/chrome_driver_setup.py
unitest/csv_reader.py
unitest/jsoncompare.py
unitest/listeners.py
unitest/uniresponse_utils.py
unitest/utilities.py
unitest-1.4.34.dist-info/LICENSE
unitest-1.4.34.dist-info/METADATA
unitest-1.4.34.dist-info/WHEEL
unitest-1.4.34.dist-info/top_level.txt
unitest-1.4.34.dist-info/RECORD
