Metadata-Version: 2.1
Name: unitest
Version: 1.4.34
Summary: Utilities required for performance and functional tests
Home-page: https://bitbucket.org/zetaengg/unitest_plutus/src/main/
Author: Zeta
Classifier: Programming Language :: Python :: 3
Classifier: License :: OSI Approved :: MIT License
Classifier: Operating System :: OS Independent
Requires-Python: >=3.6
License-File: LICENSE
